vo_wot-0.19.0.dist-info/licenses/LICENSE
vowot/__init__.py
vowot/__version__.py
vowot/cli/__init__.py
vowot/cli/cli.py
vowot/database/__init__.py
vowot/database/database_schema.py
vowot/database/influxdb_database.py
vowot/database/sqlite_database.py
vowot/functions/__init__.py
vowot/functions/functions.py
vowot/protocols/__init__.py
vowot/protocols/netconf/__init__.py
vowot/protocols/netconf/utils.py
vowot/protocols/rtsp/__init__.py
vowot/protocols/rtsp/enums.py
vowot/protocols/rtsp/server.py
vowot/protocols/rtsp/utils.py
vowot/protocols/sdn/__init__.py
vowot/protocols/sdn/utils.py
vowot/wot/__init__.py
vowot/wot/default_servient.py
vowot/wot/exposed/__init__.py
vowot/wot/exposed/influx_thing.py
vo_wot-0.19.0.dist-info/METADATA
vo_wot-0.19.0.dist-info/WHEEL
vo_wot-0.19.0.dist-info/entry_points.txt
vo_wot-0.19.0.dist-info/top_level.txt
vo_wot-0.19.0.dist-info/RECORD
