Metadata-Version: 2.4
Name: vo-wot
Version: 0.19.0
Summary: Virtual Object python implementation using a W3C WoT Runtime and the WoT Scripting API
Author-email: Andres Garcia Mangas <andres.garcia@fundacionctic.org>
Maintainer-email: Nikos Filinis <nfilinis@netmode.ntua.gr>, Dimitris Spatharakis <dspatharakis@netmode.ntua.gr>
License: MIT License
Project-URL: Documentation, https://netmode.gitlab.io/vo-wot/
Project-URL: Repository, https://gitlab.eclipse.org/eclipse-research-labs/nephele-project/vo-wot.git
Keywords: wot,iot,gateway,fog,w3c
Classifier: Development Status :: 4 - Beta
Classifier: Intended Audience :: Developers
Classifier: Natural Language :: English
Classifier: Operating System :: OS Independent
Classifier: License :: OSI Approved :: MIT License
Classifier: Programming Language :: Python :: 3.9
Classifier: Programming Language :: Python :: 3.10
Classifier: Programming Language :: Python :: 3.11
Classifier: Programming Language :: Python :: 3.12
Classifier: Programming Language :: Python :: 3.13
Requires-Python: >=3.9
License-File: LICENSE
Requires-Dist: wotpy2
Requires-Dist: influxdb-client>=1.49.0
Requires-Dist: statsmodels>=0.14.5
Requires-Dist: numpy>=2.0.2
Provides-Extra: docs
Requires-Dist: Sphinx>=7.4.7; extra == "docs"
Requires-Dist: sphinx-rtd-theme>=3.0.2; extra == "docs"
Dynamic: license-file
